{
  "title": "fn arw [ @kamui ]",
  "rules": [
    {
      "description": "fn arw",
      "manipulators": [
        {
          "type": "basic",
          "from": {
            "modifiers": {
              "mandatory": [ "fn" ]
            },
            "key_code": "w"
          },
          "to": [
            {
              "modifiers": ["control"],
              "key_code": "left_arrow"
            }
          ]
        },
        {
          "type": "basic",
          "from": {
            "modifiers": {
              "mandatory": [ "fn" ]
            },
            "key_code": "e"
          },
          "to": [
            {
              "modifiers": ["control"],
              "key_code": "right_arrow"
            }
          ]
        }
      ]
    }
  ]
}

